qt_sass_theme_getter/__init__.py
qt_sass_theme_getter/qtSassThemeGetter.py
qt_sass_theme_getter/ico/__init__.py
qt_sass_theme_getter/ico/_icons.scss
qt_sass_theme_getter/ico/check.svg
qt_sass_theme_getter/ico/close.svg
qt_sass_theme_getter/ico/dark/__init__.py
qt_sass_theme_getter/ico/dark/_icons.scss
qt_sass_theme_getter/ico/dark/check.svg
qt_sass_theme_getter/ico/dark/close.svg
qt_sass_theme_getter/ico/light/__init__.py
qt_sass_theme_getter/ico/light/_icons.scss
qt_sass_theme_getter/ico/light/check.svg
qt_sass_theme_getter/ico/light/close.svg
qt_sass_theme_getter/sass/__init__.py
qt_sass_theme_getter/sass/icon_button.scss
qt_sass_theme_getter/sass/icon_text_button.scss
qt_sass_theme_getter/sass/main_widget.scss
qt_sass_theme_getter/sass/menu_bar.scss
qt_sass_theme_getter/sass/theme.scss
qt_sass_theme_getter/var/__init__.py
qt_sass_theme_getter/var/_variables.scss
qt_sass_theme_getter/var/dark/__init__.py
qt_sass_theme_getter/var/dark/_variables.scss
qt_sass_theme_getter/var/dark_blue/__init__.py
qt_sass_theme_getter/var/dark_blue/_variables.scss
qt_sass_theme_getter/var/light/__init__.py
qt_sass_theme_getter/var/light/_variables.scss
qt_sass_theme_getter/var/light_blue/__init__.py
qt_sass_theme_getter/var/light_blue/_variables.scss
qt_sass_theme_getter-0.0.33.dist-info/LICENSE
qt_sass_theme_getter-0.0.33.dist-info/METADATA
qt_sass_theme_getter-0.0.33.dist-info/WHEEL
qt_sass_theme_getter-0.0.33.dist-info/top_level.txt
qt_sass_theme_getter-0.0.33.dist-info/RECORD
