Metadata-Version: 2.1
Name: qt-sass-theme-getter
Version: 0.0.33
Summary: Set the Qt theme (e.g. dark/light/darkblue/lightblue) easily
Home-page: https://github.com/yjg30737/qt-sass-theme-getter.git
Author: Jung Gyu Yoon
Author-email: yjg30737@gmail.com
License: MIT
Platform: UNKNOWN
License-File: LICENSE
Requires-Dist: qtsass
Requires-Dist: pyqt-svg-button (>=0.0.1)
